tractus/__init__.py
tractus/tractus.py
tractus-0.8.0.dist-info/LICENSE
tractus-0.8.0.dist-info/METADATA
tractus-0.8.0.dist-info/WHEEL
tractus-0.8.0.dist-info/top_level.txt
tractus-0.8.0.dist-info/RECORD
